odoo/addons/pos_report_session_summary/README.rst
odoo/addons/pos_report_session_summary/__init__.py
odoo/addons/pos_report_session_summary/__manifest__.py
odoo/addons/pos_report_session_summary/i18n/ca.po
odoo/addons/pos_report_session_summary/i18n/ca_ES.po
odoo/addons/pos_report_session_summary/i18n/de.po
odoo/addons/pos_report_session_summary/i18n/es.po
odoo/addons/pos_report_session_summary/i18n/fr.po
odoo/addons/pos_report_session_summary/i18n/it.po
odoo/addons/pos_report_session_summary/i18n/pos_report_session_summary.pot
odoo/addons/pos_report_session_summary/i18n/pt.po
odoo/addons/pos_report_session_summary/readme/DESCRIPTION.rst
odoo/addons/pos_report_session_summary/readme/ROADMAP.rst
odoo/addons/pos_report_session_summary/readme/USAGE.rst
odoo/addons/pos_report_session_summary/static/description/icon.png
odoo/addons/pos_report_session_summary/static/description/index.html
odoo/addons/pos_report_session_summary/views/report_session_summary.xml
odoo/addons/pos_report_session_summary/views/session_summary_report.xml
odoo_addon_pos_report_session_summary-16.0.1.0.0.3.dist-info/METADATA
odoo_addon_pos_report_session_summary-16.0.1.0.0.3.dist-info/WHEEL
odoo_addon_pos_report_session_summary-16.0.1.0.0.3.dist-info/top_level.txt
odoo_addon_pos_report_session_summary-16.0.1.0.0.3.dist-info/RECORD
